jailbreakstatus.py
jailbreakstatus-0.0.4.dist-info/LICENSE.txt
jailbreakstatus-0.0.4.dist-info/METADATA
jailbreakstatus-0.0.4.dist-info/WHEEL
jailbreakstatus-0.0.4.dist-info/entry_points.txt
jailbreakstatus-0.0.4.dist-info/top_level.txt
jailbreakstatus-0.0.4.dist-info/RECORD
