Metadata-Version: 2.1
Name: jailbreakstatus
Version: 0.0.4
Summary: Simple check for the latest jailbreak.
Home-page: https://github.com/Tatsh/jailbreakstatus
Author: Andrew Udvare
Author-email: audvare+jailbreakstatus@gmail.com
License: LICENSE.txt
Platform: UNKNOWN
Classifier: Environment :: Console
Classifier: Topic :: Utilities
Requires-Dist: requests (>=2.20.0)
